gpu4pyscf/lib/deps/lib/libxc.so
gpu4pyscf_libxc_cuda11x-0.7.dist-info/WHEEL
gpu4pyscf_libxc_cuda11x-0.7.dist-info/RECORD
gpu4pyscf_libxc_cuda11x-0.7.dist-info/top_level.txt
gpu4pyscf_libxc_cuda11x-0.7.dist-info/METADATA
