Metadata-Version: 2.1
Name: gpu4pyscf-libxc-cuda11x
Version: 0.7
Summary: Customized LibXC for GPU4PySCF
Author: PySCF developers
License: Apache-2.0
